{
    "user": [
        {
            "uid": "61563276565590",
            "countmsg": 11
        },
        {
            "uid": "61561130424674",
            "countmsg": 716
        },
        {
            "uid": "100009801367183",
            "countmsg": 418
        },
        {
            "uid": "61563793281618",
            "countmsg": 78
        },
        {
            "uid": "61554552057331",
            "countmsg": 123
        },
        {
            "uid": "61563300004313",
            "countmsg": 15
        }
    ]
}